getlibs/__init__.py
getlibs/cli.py
getlibs-2026.1.4.dist-info/licenses/LICENSE
getlibs-2026.1.4.dist-info/METADATA
getlibs-2026.1.4.dist-info/WHEEL
getlibs-2026.1.4.dist-info/entry_points.txt
getlibs-2026.1.4.dist-info/top_level.txt
getlibs-2026.1.4.dist-info/RECORD
