Metadata-Version: 2.4
Name: getlibs
Version: 2026.1.4
Summary: Python projeleri için dependency ve import analiz aracı
Author-email: Muslu Yüksektepe <musluyuksektepe@gmail.com>
Maintainer-email: Ali Alın <alialinxz@gmail.com>, Doğancan Avcı <dogancannavci@gmail.com>
License: MIT
Requires-Python: >=3.9
License-File: LICENSE
Dynamic: license-file
